xfyunsdknlp/__init__.py
xfyunsdknlp/audio_moderation_client.py
xfyunsdknlp/imagde_moderation_client.py
xfyunsdknlp/ltp_client.py
xfyunsdknlp/sa_client.py
xfyunsdknlp/sim_interp_client.py
xfyunsdknlp/text_check_client.py
xfyunsdknlp/text_moderation_client.py
xfyunsdknlp/text_proof_client.py
xfyunsdknlp/text_rewrite_client.py
xfyunsdknlp/translate_client.py
xfyunsdknlp/video_moderation_client.py
xfyunsdknlp/wordlib_client.py
xfyunsdknlp-0.0.3.dist-info/LICENSE
xfyunsdknlp-0.0.3.dist-info/METADATA
xfyunsdknlp-0.0.3.dist-info/WHEEL
xfyunsdknlp-0.0.3.dist-info/top_level.txt
xfyunsdknlp-0.0.3.dist-info/RECORD
