Metadata-Version: 2.1
Name: xfyunsdknlp
Version: 0.0.3
Summary: a sdk nlp for xfyun
Author: zyding6
Author-email: zyding6@iflytek.com
Requires-Python: >=3.7.1
License-File: LICENSE
Requires-Dist: xfyunsdkcore >=0.0.3
Requires-Dist: python-dotenv
